<?xml version="1.0" encoding="utf-8"?>
<ArrayOfAkcija xmlns:xsi="http://www.w3.org/2001/XMLSchema-instance" xmlns:xsd="http://www.w3.org/2001/XMLSchema">
  <Akcija>
    <Id>0</Id>
    <DatumPocetka>2017-01-01T00:00:00</DatumPocetka>
    <DatumZavrsetka>2017-01-01T00:00:00</DatumZavrsetka>
    <Popust>0</Popust>
    <IdNamestaja>0</IdNamestaja>
    <Obrisan>false</Obrisan>
  </Akcija>
  <Akcija>
    <Id>1</Id>
    <DatumPocetka>2017-11-27T00:00:00</DatumPocetka>
    <DatumZavrsetka>2017-12-30T00:00:00</DatumZavrsetka>
    <Popust>10002</Popust>
    <IdNamestaja>1</IdNamestaja>
    <Obrisan>false</Obrisan>
  </Akcija>
</ArrayOfAkcija>